requirements.txt
setup.cfg
setup.py
pySRE/__init__.py
pySRE/pySRE.py
pySRE.egg-info/PKG-INFO
pySRE.egg-info/SOURCES.txt
pySRE.egg-info/dependency_links.txt
pySRE.egg-info/requires.txt
pySRE.egg-info/top_level.txt
pySRE/Simple-RFC1738-Encoder/LICENSE
pySRE/Simple-RFC1738-Encoder/README.md
pySRE/Simple-RFC1738-Encoder/demo.html
pySRE/Simple-RFC1738-Encoder/css/bootstrap.min.css
pySRE/Simple-RFC1738-Encoder/css/style.css
pySRE/Simple-RFC1738-Encoder/img/asciifull.gif
pySRE/Simple-RFC1738-Encoder/js/SRE_API.js
pySRE/Simple-RFC1738-Encoder/js/common.js
pySRE/Simple-RFC1738-Encoder/js/decode.js
pySRE/Simple-RFC1738-Encoder/js/encode.js
pySRE/Simple-RFC1738-Encoder/js/utf8.js