Metadata-Version: 1.1
Name: pySRE
Version: 0.1.6
Summary: Experimental Python wrapper for Simple-RFC1738-Encoder written in JavasScript.
Home-page: https://github.com/RDCH106/pySRE
Author: Rubén de Celis Hernández
Author-email: contact@rdch106.hol.es
License: GPL v3
Download-URL: https://github.com/RDCH106/pySRE/archive/v0.1.6.tar.gz
Keywords: python-wrapper url-encoder javascript
Platform: UNKNOWN
Classifier: Programming Language :: Python
Classifier: Programming Language :: Python :: 2.7
Classifier: Programming Language :: Python :: 3.3
Classifier: Programming Language :: Python :: 3.4
Classifier: Programming Language :: Python :: 3.5
Classifier: Programming Language :: Python :: 3.6
